pidtransformer/__init__.py
pidtransformer/__pycache__/__init__.cpython-311.pyc
pidtransformer/data/__init__.py
pidtransformer/data/data_pipeline.py
pidtransformer/data/__pycache__/__init__.cpython-311.pyc
pidtransformer/data/__pycache__/data_pipeline.cpython-311.pyc
pidtransformer/models/__init__.py
pidtransformer/models/layers.py
pidtransformer/models/model.py
pidtransformer/models/__pycache__/__init__.cpython-311.pyc
pidtransformer/models/__pycache__/layers.cpython-311.pyc
pidtransformer/models/__pycache__/model.cpython-311.pyc
pidtransformer/modules/__init__.py
pidtransformer/modules/pid_controller.py
pidtransformer/modules/__pycache__/__init__.cpython-311.pyc
pidtransformer/modules/__pycache__/pid_controller.cpython-311.pyc
pidtransformer/utils/__init__.py
pidtransformer/utils/gsa.py
pidtransformer/utils/__pycache__/__init__.cpython-311.pyc
pidtransformer/utils/__pycache__/gsa.cpython-311.pyc
pidtransformer-1.0.4.dist-info/licenses/LICENSE
pidtransformer-1.0.4.dist-info/METADATA
pidtransformer-1.0.4.dist-info/WHEEL
pidtransformer-1.0.4.dist-info/top_level.txt
pidtransformer-1.0.4.dist-info/RECORD
